[
    {
        "children": [
            {
                "children": [],
                "type": "DOCKER-IMAGE-NAME:mariadb"
            }
        ],
        "type": "DOCKER-FROM"
    },
    {
        "children": [
            {
                "children": [
                    {
                        "children": [
                            {
                                "type": "ABS-MAYBE-PATH",
                                "children": []
                            },
                            {
                                "type": "ABS-PATH-ABSOLUTE",
                                "children": []
                            }
                        ],
                        "type": "DOCKER-PATH"
                    }
                ],
                "type": "DOCKER-COPY-TARGET"
            },
            {
                "children": [
                    {
                        "children": [],
                        "type": "DOCKER-PATH"
                    }
                ],
                "type": "DOCKER-COPY-SOURCE"
            }
        ],
        "type": "DOCKER-COPY"
    }
]